README.md
pyproject.toml
setup.cfg
setup.py
src/__init__.py
src/abstract_audio/__init__.py
src/abstract_audio/speech_to_text_gui.py
src/abstract_audio/audio_player/__init__.py
src/abstract_audio/audio_player/abstractaudioplayer.py
src/abstract_audio/audio_player/audioplayer_linux.py
src/abstract_audio/audio_player/audioplayer_macos.py
src/abstract_audio/audio_player/audioplayer_windows.py
src/abstract_audio/volume_states/volume_commands.py
src/abstract_audio_test.egg-info/PKG-INFO
src/abstract_audio_test.egg-info/SOURCES.txt
src/abstract_audio_test.egg-info/dependency_links.txt
src/abstract_audio_test.egg-info/requires.txt
src/abstract_audio_test.egg-info/top_level.txt