Metadata-Version: 2.1
Name: abstract-audio-test
Version: 0.0.1.13
Summary: This module provides functionalities to capture and manipulate audio input from a microphone and save them into a text file. It uses an abstract GUI to display the state of audio recording and playback..
Home-page: https://github.com/AbstractEndeavors/abstract_essentials/tree/main/abstract_audio
Author: putkoff
Author-email: partners@abstractendeavors.com
Classifier: Development Status :: 3 - Alpha
Classifier: Intended Audience :: Developers
Classifier: License :: OSI Approved :: MIT License
Classifier: Programming Language :: Python :: 3
Classifier: Programming Language :: Python :: 3.11
Requires-Python: >=3.6
